{
    "subject": "Il tuo ordine # {orderId} è stato spedito!",
    "newArrivals": "NUOVI ARRIVI",
    "woman": "DONNA",
    "man": "UOMO",
    "hallo": "Ciao %s,",
    "line1": "Ho il piacere di comunicarti che il tuo ordine è stato spedito con il corriere %s per consegna stimata 2-3 giorni lavorativi.",
    "line2": "Il codice di spedizione (tracking number) è:",
    "line3": "Puoi seguire la tua spedizione cliccando sul sito %s e ricercare la tua spedione inserendo il tuo tracking number.",
    "line4": "DETTAGLIO ORDINE",
    "line5": "Per omaggiare la decisione di averci scelto abbiamo pensato di offrirti un <span style=\"font-weight: 600\">COUPON DEL %s%%</span> che potrai utilizzare per l'acquisto di qualsiasi altro prodotto del nostro catalogo entro 10 giorni da oggi.",
    "line6": "Inserisci il coupon nel carrello:",
    "line7": "Grazie per averci scelto,"
}